src/memory.sv
`timescale 1us/1ns

module memory(
    data_out,
    address,
    data_in, 
    write_enable,
    clk
);
    parameter AddressSize = 8;
    parameter WordSize = 64;

    output logic [WordSize-1:0] data_out;
    input logic [WordSize-1:0] data_in;
    input logic [AddressSize-1:0] address;
    input logic write_enable;
    input logic clk;
    
    bit [WordSize-1:0] memory [1 << AddressSize];

    always @(negedge clk) begin
        if (write_enable) begin
            memory[address] <= data_in;
        end
        data_out <= memory[address];
    end

    bit [63:0] dump_mem_0;
    assign dump_mem_0 = memory[0];
    initial begin
        $dumpvars(0, dump_mem_0);
    end
endmodule

src/intcode.sv
`include "src/memory.sv"
`timescale 1us/1ns

module intcode(
    input logic clk,
    input logic reset,
    input logic write_program,
    input logic run_program,
    inout logic [63:0] data,
    output logic halt
);
    bit memory_write_enable;
    bit [63:0] memory_write;
    bit [63:0] memory_read;
    bit [7:0] memory_address;
    memory #(.AddressSize(8), .WordSize(64)) mem(
        .clk(clk),
        .write_enable(memory_write_enable),
        .data_in(memory_write),
        .data_out(memory_read),
        .address(memory_address)
    );
    initial $readmemh("input/input.hex", mem.memory);

    // register b00: arithmetic accumulator
    // register b01: general purpose
    // register b10: general purpose
    // register b11: instruction pointer
    bit [63:0] registers [4];

    bit [7:0] micro_instruction_pointer = '0;
    bit [7:0] micro_code [256];
    initial $readmemb("src/micro_code.bin", micro_code, 0, 255);

    enum logic [2:0] {
        RUNNING = 0,
        MEM_READ = 1,
        MEM_WRITE = 2,
        MEM_LOAD_INSTRUCTION = 3,
        HALT = 4
    } state = RUNNING;
    bit [1:0] mem_read_target;
    bit [63:0] data_output;

    integer i;

    always @ (posedge clk) begin
        bit [7:0] instruction;
        bit [1:0] target_register;
        bit [3:0] immediate_number;
        bit [1:0] operand_0;
        bit [1:0] operand_1;

        if (reset) begin
            for (i=0; i<4; i=i+1) registers[i] <= '0;
        end else if (run_program) begin
            case (state)
                RUNNING: begin
                    memory_write_enable <= 'b0;
                    $display("-------------\nInstruction %b", micro_code[micro_instruction_pointer]);
                    micro_instruction_pointer <= micro_instruction_pointer + 1;
                    instruction = micro_code[micro_instruction_pointer];
                    if (instruction[7]) begin
                        case(instruction[6:4])
                            'b000: begin
                                $display("add instruction");
                                registers[0] <= registers[0] + maths_operand(instruction[3:0]);
                            end
                            'b001: begin
                                $display("mul instruction");
                                registers[0] <= registers[0] * maths_operand(instruction[3:0]);
                            end
                            default: $display("Unknown maths instruction");
                        endcase
                    end else if (instruction[6]) begin
                        $display("load immediate instruction");
                        registers[instruction[5:4]] <= {60'b0, instruction[3:0]};
                    end else begin
                        case (instruction[5:4])
                            'b00: begin
                                $display("mv r%d <- r%d", instruction[3:2], instruction[1:0]);
                                registers[instruction[3:2]] <= registers[instruction[1:0]];
                            end
                            'b01: begin
                                $display("ld r%d <- %%r%d (*%d)", instruction[3:2], instruction[1:0], registers[instruction[1:0]]);
                                memory_address <= registers[instruction[1:0]];
                                mem_read_target <= instruction[3:2];
                                state <= MEM_READ;
                            end
                            'b10: begin
                                $display("st %%r%d (*%d) <- r%d (%d)",
                                    instruction[3:2],
                                    registers[instruction[3:2]],
                                    instruction[1:0],
                                    registers[instruction[1:0]]
                                );
                                memory_address <= registers[instruction[3:2]];
                                memory_write <= registers[instruction[1:0]];
                                state <= MEM_WRITE;
                            end
                            'b11: begin
                                case (instruction[3:2])
                                    'b11: begin
                                        case (instruction[1:0])
                                            'b10: begin
                                                $display("next");
                                                memory_address <= registers[3];
                                                state <= MEM_LOAD_INSTRUCTION;
                                            end
                                            'b11: begin
                                                $display("halt");
                                                state <= HALT;
                                                data_output <= registers[0];
                                            end
                                        endcase
                                    end
                                endcase
                            end
                        endcase
                    end
                end
                MEM_READ: begin
                    $display("memory read: %d -> r%d", memory_read, mem_read_target);
                    registers[mem_read_target] <= memory_read;
                    state <= RUNNING;
                end
                MEM_WRITE: begin
                    $display("writing memory");
                    memory_write_enable <= 'b1;
                    state <= RUNNING;
                end
                MEM_LOAD_INSTRUCTION: begin
                    $display("loading instruction");
                    case (memory_read)
                        1: begin
                            $display("\n\nExecuting 1: Add");
                            micro_instruction_pointer <= 1;
                        end
                        2: begin
                            $display("\n\nExecuting 2: Multiply");
                            micro_instruction_pointer <= 17;
                        end
                        99: begin
                            $display("\n\nExecuting 99: Halt");
                            micro_instruction_pointer <= 33;
                        end
                    endcase
                    state <= RUNNING;
                end
            endcase
        end
    end

    function [63:0] maths_operand;
        input [3:0] operand;
        if (operand[3] == 'b0) begin
            $display("maths operand immediate %d", operand[2:0]);
            maths_operand = {61'b0, operand[2:0]};
        end else begin
            $display("maths operand register %d", operand[1:0]);
            maths_operand = registers[operand[1:0]];
        end
    endfunction

    assign halt = state == HALT;
    assign data = state == HALT ? data_output : 'z;

    bit [63:0] dump_register_0;
    assign dump_register_0 = registers[0];
    initial begin
        $dumpvars(0, dump_register_0);
    end
    bit [63:0] dump_register_1;
    assign dump_register_1 = registers[1];
    initial begin
        $dumpvars(0, dump_register_1);
    end
    bit [63:0] dump_register_2;
    assign dump_register_2 = registers[2];
    initial begin
        $dumpvars(0, dump_register_2);
    end
    bit [63:0] dump_register_3;
    assign dump_register_3 = registers[3];
    initial begin
        $dumpvars(0, dump_register_3);
    end

endmodule // intcode

src/testbench.sv
`include "src/intcode.sv"
`timescale 1us/1ns

module testbench;
    logic clk = 'b0;
    logic reset = 'b0;
    logic write_program = 'b0;
    logic run_program = 'b0;
    logic [64] data;
    logic halt;
 
    // Instantiate the Unit Under Test (UUT)
    intcode UUT(
        .clk(clk),
        .reset(reset),
        .write_program(write_program),
        .run_program(run_program),
        .data(data),
        .halt(halt)
    );
     
    always #20 clk <= !clk;
         
    initial begin
        $dumpvars(0,testbench);

        run_program <= 1'b1;
        
        while (!halt) begin
            #1000;
        end
        
        run_program <= 1'b0;
        #100

        $display("Result: %d", data);

        $finish();
    end
     
endmodule

dump.vcd
$date
	Mon Dec  2 19:22:33 2019
$end
$version
	Icarus Verilog
$end
$timescale
	1ns
$end
$scope module testbench $end
$scope module UUT $end
$scope module mem $end
$var wire 64 ! dump_mem_0 [63:0] $end
$upscope $end
$upscope $end
$upscope $end
$scope module testbench $end
$scope module UUT $end
$var wire 64 " dump_register_0 [63:0] $end
$upscope $end
$upscope $end
$scope module testbench $end
$scope module UUT $end
$var wire 64 # dump_register_1 [63:0] $end
$upscope $end
$upscope $end
$scope module testbench $end
$scope module UUT $end
$var wire 64 $ dump_register_2 [63:0] $end
$upscope $end
$upscope $end
$scope module testbench $end
$scope module UUT $end
$var wire 64 % dump_register_3 [63:0] $end
$upscope $end
$upscope $end
$scope module testbench $end
$var wire 1 & halt $end
$var wire 64 ' data [0:63] $end
$var reg 1 ( clk $end
$var reg 1 ) reset $end
$var reg 1 * run_program $end
$var reg 1 + write_program $end
$scope module UUT $end
$var wire 1 ( clk $end
$var wire 1 ) reset $end
$var wire 1 * run_program $end
$var wire 1 + write_program $end
$var wire 64 , memory_read [63:0] $end
$var wire 1 & halt $end
$var wire 64 - data [63:0] $end
$var reg 3 . state [2:0] $end
$var reg 64 / data_output [63:0] $end
$var integer 32 0 i [31:0] $end
$var reg 2 1 mem_read_target [1:0] $end
$var reg 8 2 memory_address [7:0] $end
$var reg 64 3 memory_write [63:0] $end
$var reg 1 4 memory_write_enable $end
$var reg 8 5 micro_instruction_pointer [7:0] $end
$scope function maths_operand $end
$var reg 64 6 maths_operand [63:0] $end
$var reg 4 7 operand [3:0] $end
$upscope $end
$scope module mem $end
$var wire 8 8 address [7:0] $end
$var wire 1 ( clk $end
$var wire 64 9 data_in [63:0] $end
$var wire 1 4 write_enable $end
$var reg 64 : data_out [63:0] $end
$upscope $end
$scope begin $unm_blk_4 $end
$var reg 8 ; instruction [7:0] $end
$upscope $end
$upscope $end
$upscope $end
$enddefinitions $end
#0
$dumpvars
b0 ;
bx :
b0 9
b0 8
bx 7
bx 6
b0 5
04
b0 3
b0 2
b0 1
bx 0
b0 /
b0 .
bz -
b0 ,
0+
1*
0)
0(
bz '
0&
b0 %
b0 $
b0 #
b0 "
b1 !
$end
#20000
b11 .
b1 5
b111110 ;
1(
#40000
b1 ,
b1 :
0(
#60000
b0 .
1(
#80000
0(
#100000
b0 "
b10 5
b11 ;
1(
#120000
0(
#140000
b1 "
b11 5
b1 6
b1 7
b10000001 ;
1(
#160000
0(
#180000
b1 .
b1 1
b1 2
b1 8
b100 5
b10100 ;
1(
#200000
b1100 ,
b1100 :
0(
#220000
b0 .
b1100 #
1(
#240000
0(
#260000
b1 .
b1100 2
b1100 8
b101 5
b10101 ;
1(
#280000
b1 ,
b1 :
0(
#300000
b0 .
b1 #
1(
#320000
0(
#340000
b10 "
b110 5
b10000001 ;
1(
#360000
0(
#380000
b1 .
b0 1
b10 2
b10 8
b111 5
b10000 ;
1(
#400000
b10 ,
b10 :
0(
#420000
b0 .
1(
#440000
0(
#460000
b1 .
b1000 5
1(
#480000
0(
#500000
b0 .
1(
#520000
0(
#540000
b11 "
b1001 5
b1101 7
b10001101 ;
1(
#560000
0(
#580000
b11 #
b1010 5
b100 ;
1(
#600000
0(
#620000
b0 "
b1011 5
b11 ;
1(
#640000
0(
#660000
b11 "
b1100 5
b11 6
b11 7
b10000011 ;
1(
#680000
0(
#700000
b1 .
b10 1
b11 2
b11 8
b1101 5
b11000 ;
1(
#720000
b11 ,
b11 :
0(
#740000
b0 .
b11 $
1(
#760000
0(
#780000
b10 .
b11 3
b11 9
b1110 5
b101001 ;
1(
#800000
0(
#820000
b0 .
14
1(
#840000
0(
#860000
b100 "
b1111 5
04
b1 6
b1 7
b10000001 ;
1(
#880000
0(
#900000
b100 %
b10000 5
b1100 ;
1(
#920000
0(
#940000
b11 .
b100 2
b100 8
b10001 5
b111110 ;
1(
#960000
b1 ,
b1 :
0(
#980000
b0 .
b1 5
1(
#1000000
0(
#1020000
b10 5
b11 ;
1(
#1040000
0(
#1060000
b101 "
b11 5
b10000001 ;
1(
#1080000
0(
#1100000
b1 .
b1 1
b101 2
b101 8
b100 5
b10100 ;
1(
#1120000
0(
#1140000
b0 .
b1 #
1(
#1160000
0(
#1180000
b1 .
b1 2
b1 8
b101 5
b10101 ;
1(
#1200000
b1100 ,
b1100 :
0(
#1220000
b0 .
b1100 #
1(
#1240000
0(
#1260000
b110 "
b110 5
b10000001 ;
1(
#1280000
0(
#1300000
b1 .
b0 1
b110 2
b110 8
b111 5
b10000 ;
1(
#1320000
b10 ,
b10 :
0(
#1340000
b0 .
b10 "
1(
#1360000
0(
#1380000
b1 .
b10 2
b10 8
b1000 5
1(
#1400000
0(
#1420000
b0 .
1(
#1440000
0(
#1460000
b1110 "
b1001 5
b1100 6
b1101 7
b10001101 ;
1(
#1480000
0(
#1500000
b1110 #
b1010 5
b100 ;
1(
#1520000
0(
#1540000
b100 "
b1011 5
b11 ;
1(
#1560000
0(
#1580000
b111 "
b1100 5
b11 6
b11 7
b10000011 ;
1(
#1600000
0(
#1620000
b1 .
b10 1
b111 2
b111 8
b1101 5
b11000 ;
1(
#1640000
b11 ,
b11 :
0(
#1660000
b0 .
1(
#1680000
0(
#1700000
b10 .
b1110 3
b1110 9
b11 2
b11 8
b1110 5
b101001 ;
1(
#1720000
0(
#1740000
b0 .
14
1(
#1760000
0(
#1780000
b1000 "
b1111 5
04
b1 6
b1 7
b10000001 ;
1(
#1800000
b1110 ,
b1110 :
0(
#1820000
b1000 %
b10000 5
b1100 ;
1(
#1840000
0(
#1860000
b11 .
b1000 2
b1000 8
b10001 5
b111110 ;
1(
#1880000
b1 ,
b1 :
0(
#1900000
b0 .
b1 5
1(
#1920000
0(
#1940000
b10 5
b11 ;
1(
#1960000
0(
#1980000
b1001 "
b11 5
b10000001 ;
1(
#2000000
0(
#2020000
b1 .
b1 1
b1001 2
b1001 8
b100 5
b10100 ;
1(
#2040000
b11 ,
b11 :
0(
#2060000
b0 .
b11 #
1(
#2080000
0(
#2100000
b1 .
b11 2
b11 8
b101 5
b10101 ;
1(
#2120000
b1110 ,
b1110 :
0(
#2140000
b0 .
b1110 #
1(
#2160000
0(
#2180000
b1010 "
b110 5
b10000001 ;
1(
#2200000
0(
#2220000
b1 .
b0 1
b1010 2
b1010 8
b111 5
b10000 ;
1(
#2240000
b100 ,
b100 :
0(
#2260000
b0 .
b100 "
1(
#2280000
0(
#2300000
b1 .
b100 2
b100 8
b1000 5
1(
#2320000
b1 ,
b1 :
0(
#2340000
b0 .
b1 "
1(
#2360000
0(
#2380000
b1111 "
b1001 5
b1110 6
b1101 7
b10001101 ;
1(
#2400000
0(
#2420000
b1111 #
b1010 5
b100 ;
1(
#2440000
0(
#2460000
b1000 "
b1011 5
b11 ;
1(
#2480000
0(
#2500000
b1011 "
b1100 5
b11 6
b11 7
b10000011 ;
1(
#2520000
0(
#2540000
b1 .
b10 1
b1011 2
b1011 8
b1101 5
b11000 ;
1(
#2560000
b11 ,
b11 :
0(
#2580000
b0 .
1(
#2600000
0(
#2620000
b10 .
b1111 3
b1111 9
b11 2
b11 8
b1110 5
b101001 ;
1(
#2640000
b1110 ,
b1110 :
0(
#2660000
b0 .
14
1(
#2680000
0(
#2700000
b1100 "
b1111 5
04
b1 6
b1 7
b10000001 ;
1(
#2720000
b1111 ,
b1111 :
0(
#2740000
b1100 %
b10000 5
b1100 ;
1(
#2760000
0(
#2780000
b11 .
b1100 2
b1100 8
b10001 5
b111110 ;
1(
#2800000
b1 ,
b1 :
0(
#2820000
b0 .
b1 5
1(
#2840000
0(
#2860000
b10 5
b11 ;
1(
#2880000
0(
#2900000
b1101 "
b11 5
b10000001 ;
1(
#2920000
0(
#2940000
b1 .
b1 1
b1101 2
b1101 8
b100 5
b10100 ;
1(
#2960000
b101 ,
b101 :
0(
#2980000
b0 .
b101 #
1(
#3000000
0(
#3020000
b1 .
b101 2
b101 8
b101 5
b10101 ;
1(
#3040000
b1 ,
b1 :
0(
#3060000
b0 .
b1 #
1(
#3080000
0(
#3100000
b1110 "
b110 5
b10000001 ;
1(
#3120000
0(
#3140000
b1 .
b0 1
b1110 2
b1110 8
b111 5
b10000 ;
1(
#3160000
b0 ,
b0 :
0(
#3180000
b0 .
b0 "
1(
#3200000
0(
#3220000
b1 .
b0 2
b0 8
b1000 5
1(
#3240000
b1 ,
b1 :
0(
#3260000
b0 .
b1 "
1(
#3280000
0(
#3300000
b10 "
b1001 5
b1101 7
b10001101 ;
1(
#3320000
0(
#3340000
b10 #
b1010 5
b100 ;
1(
#3360000
0(
#3380000
b1100 "
b1011 5
b11 ;
1(
#3400000
0(
#3420000
b1111 "
b1100 5
b11 6
b11 7
b10000011 ;
1(
#3440000
0(
#3460000
b1 .
b10 1
b1111 2
b1111 8
b1101 5
b11000 ;
1(
#3480000
b11 ,
b11 :
0(
#3500000
b0 .
1(
#3520000
0(
#3540000
b10 .
b10 3
b10 9
b11 2
b11 8
b1110 5
b101001 ;
1(
#3560000
b1111 ,
b1111 :
0(
#3580000
b0 .
14
1(
#3600000
0(
#3620000
b10000 "
b1111 5
04
b1 6
b1 7
b10000001 ;
1(
#3640000
b10 ,
b10 :
0(
#3660000
b10000 %
b10000 5
b1100 ;
1(
#3680000
0(
#3700000
b11 .
b10000 2
b10000 8
b10001 5
b111110 ;
1(
#3720000
0(
#3740000
b0 .
1(
#3760000
0(
#3780000
b10010 5
b11 ;
1(
#3800000
0(
#3820000
b10001 "
b10011 5
b10000001 ;
1(
#3840000
0(
#3860000
b1 .
b1 1
b10001 2
b10001 8
b10100 5
b10100 ;
1(
#3880000
b1010 ,
b1010 :
0(
#3900000
b0 .
b1010 #
1(
#3920000
0(
#3940000
b1 .
b1010 2
b1010 8
b10101 5
b10101 ;
1(
#3960000
b100 ,
b100 :
0(
#3980000
b0 .
b100 #
1(
#4000000
0(
#4020000
b10010 "
b10110 5
b10000001 ;
1(
#4040000
0(
#4060000
b1 .
b0 1
b10010 2
b10010 8
b10111 5
b10000 ;
1(
#4080000
b1 ,
b1 :
0(
#4100000
b0 .
b1 "
1(
#4120000
0(
#4140000
b1 .
b1 2
b1 8
b11000 5
1(
#4160000
b1100 ,
b1100 :
0(
#4180000
b0 .
b1100 "
1(
#4200000
0(
#4220000
b110000 "
b11001 5
b100 6
b1101 7
b10011101 ;
1(
#4240000
0(
#4260000
b110000 #
b11010 5
b100 ;
1(
#4280000
0(
#4300000
b10000 "
b11011 5
b11 ;
1(
#4320000
0(
#4340000
b10011 "
b11100 5
b11 6
b11 7
b10000011 ;
1(
#4360000
0(
#4380000
b1 .
b10 1
b10011 2
b10011 8
b11101 5
b11000 ;
1(
#4400000
b10011 ,
b10011 :
0(
#4420000
b0 .
b10011 $
1(
#4440000
0(
#4460000
b10 .
b110000 3
b110000 9
b11110 5
b101001 ;
1(
#4480000
0(
#4500000
b0 .
14
1(
#4520000
0(
#4540000
b10100 "
b11111 5
04
b1 6
b1 7
b10000001 ;
1(
#4560000
b110000 ,
b110000 :
0(
#4580000
b10100 %
b100000 5
b1100 ;
1(
#4600000
0(
#4620000
b11 .
b10100 2
b10100 8
b100001 5
b111110 ;
1(
#4640000
b1 ,
b1 :
0(
#4660000
b0 .
b1 5
1(
#4680000
0(
#4700000
b10 5
b11 ;
1(
#4720000
0(
#4740000
b10101 "
b11 5
b10000001 ;
1(
#4760000
0(
#4780000
b1 .
b1 1
b10101 2
b10101 8
b100 5
b10100 ;
1(
#4800000
b110 ,
b110 :
0(
#4820000
b0 .
b110 #
1(
#4840000
0(
#4860000
b1 .
b110 2
b110 8
b101 5
b10101 ;
1(
#4880000
b10 ,
b10 :
0(
#4900000
b0 .
b10 #
1(
#4920000
0(
#4940000
b10110 "
b110 5
b10000001 ;
1(
#4960000
0(
#4980000
b1 .
b0 1
b10110 2
b10110 8
b111 5
b10000 ;
1(
#5000000
b10011 ,
b10011 :
0(
#5020000
b0 .
b10011 "
1(
#5040000
0(
#5060000
b1 .
b10011 2
b10011 8
b1000 5
1(
#5080000
b110000 ,
b110000 :
0(
#5100000
b0 .
b110000 "
1(
#5120000
0(
#5140000
b110010 "
b1001 5
b10 6
b1101 7
b10001101 ;
1(
#5160000
0(
#5180000
b110010 #
b1010 5
b100 ;
1(
#5200000
0(
#5220000
b10100 "
b1011 5
b11 ;
1(
#5240000
0(
#5260000
b10111 "
b1100 5
b11 6
b11 7
b10000011 ;
1(
#5280000
0(
#5300000
b1 .
b10 1
b10111 2
b10111 8
b1101 5
b11000 ;
1(
#5320000
b10111 ,
b10111 :
0(
#5340000
b0 .
b10111 $
1(
#5360000
0(
#5380000
b10 .
b110010 3
b110010 9
b1110 5
b101001 ;
1(
#5400000
0(
#5420000
b0 .
14
1(
#5440000
0(
#5460000
b11000 "
b1111 5
04
b1 6
b1 7
b10000001 ;
1(
#5480000
b110010 ,
b110010 :
0(
#5500000
b11000 %
b10000 5
b1100 ;
1(
#5520000
0(
#5540000
b11 .
b11000 2
b11000 8
b10001 5
b111110 ;
1(
#5560000
b1 ,
b1 :
0(
#5580000
b0 .
b1 5
1(
#5600000
0(
#5620000
b10 5
b11 ;
1(
#5640000
0(
#5660000
b11001 "
b11 5
b10000001 ;
1(
#5680000
0(
#5700000
b1 .
b1 1
b11001 2
b11001 8
b100 5
b10100 ;
1(
#5720000
b10111 ,
b10111 :
0(
#5740000
b0 .
b10111 #
1(
#5760000
0(
#5780000
b1 .
b10111 2
b10111 8
b101 5
b10101 ;
1(
#5800000
b110010 ,
b110010 :
0(
#5820000
b0 .
b110010 #
1(
#5840000
0(
#5860000
b11010 "
b110 5
b10000001 ;
1(
#5880000
0(
#5900000
b1 .
b0 1
b11010 2
b11010 8
b111 5
b10000 ;
1(
#5920000
b1101 ,
b1101 :
0(
#5940000
b0 .
b1101 "
1(
#5960000
0(
#5980000
b1 .
b1101 2
b1101 8
b1000 5
1(
#6000000
b101 ,
b101 :
0(
#6020000
b0 .
b101 "
1(
#6040000
0(
#6060000
b110111 "
b1001 5
b110010 6
b1101 7
b10001101 ;
1(
#6080000
0(
#6100000
b110111 #
b1010 5
b100 ;
1(
#6120000
0(
#6140000
b11000 "
b1011 5
b11 ;
1(
#6160000
0(
#6180000
b11011 "
b1100 5
b11 6
b11 7
b10000011 ;
1(
#6200000
0(
#6220000
b1 .
b10 1
b11011 2
b11011 8
b1101 5
b11000 ;
1(
#6240000
b11011 ,
b11011 :
0(
#6260000
b0 .
b11011 $
1(
#6280000
0(
#6300000
b10 .
b110111 3
b110111 9
b1110 5
b101001 ;
1(
#6320000
0(
#6340000
b0 .
14
1(
#6360000
0(
#6380000
b11100 "
b1111 5
04
b1 6
b1 7
b10000001 ;
1(
#6400000
b110111 ,
b110111 :
0(
#6420000
b11100 %
b10000 5
b1100 ;
1(
#6440000
0(
#6460000
b11 .
b11100 2
b11100 8
b10001 5
b111110 ;
1(
#6480000
b10 ,
b10 :
0(
#6500000
b0 .
1(
#6520000
0(
#6540000
b10010 5
b11 ;
1(
#6560000
0(
#6580000
b11101 "
b10011 5
b10000001 ;
1(
#6600000
0(
#6620000
b1 .
b1 1
b11101 2
b11101 8
b10100 5
b10100 ;
1(
#6640000
b110 ,
b110 :
0(
#6660000
b0 .
b110 #
1(
#6680000
0(
#6700000
b1 .
b110 2
b110 8
b10101 5
b10101 ;
1(
#6720000
b10 ,
b10 :
0(
#6740000
b0 .
b10 #
1(
#6760000
0(
#6780000
b11110 "
b10110 5
b10000001 ;
1(
#6800000
0(
#6820000
b1 .
b0 1
b11110 2
b11110 8
b10111 5
b10000 ;
1(
#6840000
b11011 ,
b11011 :
0(
#6860000
b0 .
b11011 "
1(
#6880000
0(
#6900000
b1 .
b11011 2
b11011 8
b11000 5
1(
#6920000
b110111 ,
b110111 :
0(
#6940000
b0 .
b110111 "
1(
#6960000
0(
#6980000
b1101110 "
b11001 5
b10 6
b1101 7
b10011101 ;
1(
#7000000
0(
#7020000
b1101110 #
b11010 5
b100 ;
1(
#7040000
0(
#7060000
b11100 "
b11011 5
b11 ;
1(
#7080000
0(
#7100000
b11111 "
b11100 5
b11 6
b11 7
b10000011 ;
1(
#7120000
0(
#7140000
b1 .
b10 1
b11111 2
b11111 8
b11101 5
b11000 ;
1(
#7160000
b11111 ,
b11111 :
0(
#7180000
b0 .
b11111 $
1(
#7200000
0(
#7220000
b10 .
b1101110 3
b1101110 9
b11110 5
b101001 ;
1(
#7240000
0(
#7260000
b0 .
14
1(
#7280000
0(
#7300000
b100000 "
b11111 5
04
b1 6
b1 7
b10000001 ;
1(
#7320000
b1101110 ,
b1101110 :
0(
#7340000
b100000 %
b100000 5
b1100 ;
1(
#7360000
0(
#7380000
b11 .
b100000 2
b100000 8
b100001 5
b111110 ;
1(
#7400000
b1 ,
b1 :
0(
#7420000
b0 .
b1 5
1(
#7440000
0(
#7460000
b10 5
b11 ;
1(
#7480000
0(
#7500000
b100001 "
b11 5
b10000001 ;
1(
#7520000
0(
#7540000
b1 .
b1 1
b100001 2
b100001 8
b100 5
b10100 ;
1(
#7560000
b101 ,
b101 :
0(
#7580000
b0 .
b101 #
1(
#7600000
0(
#7620000
b1 .
b101 2
b101 8
b101 5
b10101 ;
1(
#7640000
b1 ,
b1 :
0(
#7660000
b0 .
b1 #
1(
#7680000
0(
#7700000
b100010 "
b110 5
b10000001 ;
1(
#7720000
0(
#7740000
b1 .
b0 1
b100010 2
b100010 8
b111 5
b10000 ;
1(
#7760000
b11111 ,
b11111 :
0(
#7780000
b0 .
b11111 "
1(
#7800000
0(
#7820000
b1 .
b11111 2
b11111 8
b1000 5
1(
#7840000
b1101110 ,
b1101110 :
0(
#7860000
b0 .
b1101110 "
1(
#7880000
0(
#7900000
b1101111 "
b1001 5
b1101 7
b10001101 ;
1(
#7920000
0(
#7940000
b1101111 #
b1010 5
b100 ;
1(
#7960000
0(
#7980000
b100000 "
b1011 5
b11 ;
1(
#8000000
0(
#8020000
b100011 "
b1100 5
b11 6
b11 7
b10000011 ;
1(
#8040000
0(
#8060000
b1 .
b10 1
b100011 2
b100011 8
b1101 5
b11000 ;
1(
#8080000
b100011 ,
b100011 :
0(
#8100000
b0 .
b100011 $
1(
#8120000
0(
#8140000
b10 .
b1101111 3
b1101111 9
b1110 5
b101001 ;
1(
#8160000
0(
#8180000
b0 .
14
1(
#8200000
0(
#8220000
b100100 "
b1111 5
04
b1 6
b1 7
b10000001 ;
1(
#8240000
b1101111 ,
b1101111 :
0(
#8260000
b100100 %
b10000 5
b1100 ;
1(
#8280000
0(
#8300000
b11 .
b100100 2
b100100 8
b10001 5
b111110 ;
1(
#8320000
b10 ,
b10 :
0(
#8340000
b0 .
1(
#8360000
0(
#8380000
b10010 5
b11 ;
1(
#8400000
0(
#8420000
b100101 "
b10011 5
b10000001 ;
1(
#8440000
0(
#8460000
b1 .
b1 1
b100101 2
b100101 8
b10100 5
b10100 ;
1(
#8480000
b1010 ,
b1010 :
0(
#8500000
b0 .
b1010 #
1(
#8520000
0(
#8540000
b1 .
b1010 2
b1010 8
b10101 5
b10101 ;
1(
#8560000
b100 ,
b100 :
0(
#8580000
b0 .
b100 #
1(
#8600000
0(
#8620000
b100110 "
b10110 5
b10000001 ;
1(
#8640000
0(
#8660000
b1 .
b0 1
b100110 2
b100110 8
b10111 5
b10000 ;
1(
#8680000
b100011 ,
b100011 :
0(
#8700000
b0 .
b100011 "
1(
#8720000
0(
#8740000
b1 .
b100011 2
b100011 8
b11000 5
1(
#8760000
b1101111 ,
b1101111 :
0(
#8780000
b0 .
b1101111 "
1(
#8800000
0(
#8820000
b110111100 "
b11001 5
b100 6
b1101 7
b10011101 ;
1(
#8840000
0(
#8860000
b110111100 #
b11010 5
b100 ;
1(
#8880000
0(
#8900000
b100100 "
b11011 5
b11 ;
1(
#8920000
0(
#8940000
b100111 "
b11100 5
b11 6
b11 7
b10000011 ;
1(
#8960000
0(
#8980000
b1 .
b10 1
b100111 2
b100111 8
b11101 5
b11000 ;
1(
#9000000
b100111 ,
b100111 :
0(
#9020000
b0 .
b100111 $
1(
#9040000
0(
#9060000
b10 .
b110111100 3
b110111100 9
b11110 5
b101001 ;
1(
#9080000
0(
#9100000
b0 .
14
1(
#9120000
0(
#9140000
b101000 "
b11111 5
04
b1 6
b1 7
b10000001 ;
1(
#9160000
b110111100 ,
b110111100 :
0(
#9180000
b101000 %
b100000 5
b1100 ;
1(
#9200000
0(
#9220000
b11 .
b101000 2
b101000 8
b100001 5
b111110 ;
1(
#9240000
b1 ,
b1 :
0(
#9260000
b0 .
b1 5
1(
#9280000
0(
#9300000
b10 5
b11 ;
1(
#9320000
0(
#9340000
b101001 "
b11 5
b10000001 ;
1(
#9360000
0(
#9380000
b1 .
b1 1
b101001 2
b101001 8
b100 5
b10100 ;
1(
#9400000
b110 ,
b110 :
0(
#9420000
b0 .
b110 #
1(
#9440000
0(
#9460000
b1 .
b110 2
b110 8
b101 5
b10101 ;
1(
#9480000
b10 ,
b10 :
0(
#9500000
b0 .
b10 #
1(
#9520000
0(
#9540000
b101010 "
b110 5
b10000001 ;
1(
#9560000
0(
#9580000
b1 .
b0 1
b101010 2
b101010 8
b111 5
b10000 ;
1(
#9600000
b100111 ,
b100111 :
0(
#9620000
b0 .
b100111 "
1(
#9640000
0(
#9660000
b1 .
b100111 2
b100111 8
b1000 5
1(
#9680000
b110111100 ,
b110111100 :
0(
#9700000
b0 .
b110111100 "
1(
#9720000
0(
#9740000
b110111110 "
b1001 5
b10 6
b1101 7
b10001101 ;
1(
#9760000
0(
#9780000
b110111110 #
b1010 5
b100 ;
1(
#9800000
0(
#9820000
b101000 "
b1011 5
b11 ;
1(
#9840000
0(
#9860000
b101011 "
b1100 5
b11 6
b11 7
b10000011 ;
1(
#9880000
0(
#9900000
b1 .
b10 1
b101011 2
b101011 8
b1101 5
b11000 ;
1(
#9920000
b101011 ,
b101011 :
0(
#9940000
b0 .
b101011 $
1(
#9960000
0(
#9980000
b10 .
b110111110 3
b110111110 9
b1110 5
b101001 ;
1(
#10000000
0(
#10020000
b0 .
14
1(
#10040000
0(
#10060000
b101100 "
b1111 5
04
b1 6
b1 7
b10000001 ;
1(
#10080000
b110111110 ,
b110111110 :
0(
#10100000
b101100 %
b10000 5
b1100 ;
1(
#10120000
0(
#10140000
b11 .
b101100 2
b101100 8
b10001 5
b111110 ;
1(
#10160000
b1 ,
b1 :
0(
#10180000
b0 .
b1 5
1(
#10200000
0(
#10220000
b10 5
b11 ;
1(
#10240000
0(
#10260000
b101101 "
b11 5
b10000001 ;
1(
#10280000
0(
#10300000
b1 .
b1 1
b101101 2
b101101 8
b100 5
b10100 ;
1(
#10320000
b1101 ,
b1101 :
0(
#10340000
b0 .
b1101 #
1(
#10360000
0(
#10380000
b1 .
b1101 2
b1101 8
b101 5
b10101 ;
1(
#10400000
b101 ,
b101 :
0(
#10420000
b0 .
b101 #
1(
#10440000
0(
#10460000
b101110 "
b110 5
b10000001 ;
1(
#10480000
0(
#10500000
b1 .
b0 1
b101110 2
b101110 8
b111 5
b10000 ;
1(
#10520000
b101011 ,
b101011 :
0(
#10540000
b0 .
b101011 "
1(
#10560000
0(
#10580000
b1 .
b101011 2
b101011 8
b1000 5
1(
#10600000
b110111110 ,
b110111110 :
0(
#10620000
b0 .
b110111110 "
1(
#10640000
0(
#10660000
b111000011 "
b1001 5
b101 6
b1101 7
b10001101 ;
1(
#10680000
0(
#10700000
b111000011 #
b1010 5
b100 ;
1(
#10720000
0(
#10740000
b101100 "
b1011 5
b11 ;
1(
#10760000
0(
#10780000
b101111 "
b1100 5
b11 6
b11 7
b10000011 ;
1(
#10800000
0(
#10820000
b1 .
b10 1
b101111 2
b101111 8
b1101 5
b11000 ;
1(
#10840000
b101111 ,
b101111 :
0(
#10860000
b0 .
b101111 $
1(
#10880000
0(
